Rusthonian-0.2.0.dist-info/METADATA
Rusthonian-0.2.0.dist-info/WHEEL
Rusthonian-0.2.0.dist-info/licenses/LICENSE-APACHE
Rusthonian-0.2.0.dist-info/licenses/LICENSE-MIT
Rusthonian/__init__.py
Rusthonian/py.typed
Rusthonian/rusthonian.cpython-313-x86_64-linux-gnu.so
Rusthonian-0.2.0.dist-info/RECORD
