Metadata-Version: 2.4
Name: Rusthonian
Version: 0.2.0
Classifier: Development Status :: 4 - Beta
Classifier: Intended Audience :: Developers
Classifier: License :: OSI Approved :: MIT License
Classifier: License :: OSI Approved :: Apache Software License
Classifier: Operating System :: OS Independent
Classifier: Programming Language :: Python :: 3
Classifier: Programming Language :: Python :: 3.9
Classifier: Programming Language :: Python :: 3.10
Classifier: Programming Language :: Python :: 3.11
Classifier: Programming Language :: Python :: 3.12
Classifier: Programming Language :: Python :: 3.13
Classifier: Programming Language :: Rust
Classifier: Topic :: Software Development :: Libraries :: Python Modules
Classifier: Topic :: System :: Distributed Computing
Classifier: Typing :: Typed
Requires-Dist: pytest>=7.0 ; extra == 'dev'
Requires-Dist: pytest-benchmark>=4.0 ; extra == 'dev'
Requires-Dist: mypy>=1.0 ; extra == 'dev'
Provides-Extra: dev
License-File: LICENSE-APACHE
License-File: LICENSE-MIT
Summary: High-performance Python bindings for Rust crates (UUID, Chrono, and more)
Keywords: rust,python,bindings,rusthonian,uuid,chrono,datetime,performance
Author-email: Rusthonian Team <contact@rusthonian.org>
Maintainer-email: Rusthonian Team <contact@rusthonian.org>
License: MIT OR Apache-2.0
Requires-Python: >=3.9
Project-URL: Homepage, https://github.com/Rusthonian/Rusthonian
Project-URL: Documentation, https://github.com/Rusthonian/Rusthonian#readme
Project-URL: Repository, https://github.com/Rusthonian/Rusthonian
Project-URL: Bug Tracker, https://github.com/Rusthonian/Rusthonian/issues
Project-URL: Changelog, https://github.com/Rusthonian/Rusthonian/releases
